Metadata-Version: 1.2
Name: peakingduck
Version: 0.0.1
Summary: A peak finding library leveraging AI written in C++14 with python bindings
Home-page: https://github.com/thomasms/peakingduck
Author: Thomas Stainer
Author-email: me@physicstom.com
License: MIT
Platform: UNKNOWN
Requires-Python: >=3
